deepl_scraper_pp2/__init__.py
deepl_scraper_pp2/deepl_server.py
deepl_scraper_pp2/deepl_tr.py
deepl_scraper_pp2/get_ppbrowser.py-
deepl_scraper_pp2/run_uvicorn.py
deepl_scraper_pp2-0.1.0a2.dist-info/WHEEL
deepl_scraper_pp2-0.1.0a2.dist-info/METADATA
deepl_scraper_pp2-0.1.0a2.dist-info/RECORD
