Metadata-Version: 2.1
Name: deepl-scraper-pp2
Version: 0.1.0a2
Summary: scrape deepl via pyppeteer2 with para info
Home-page: https://github.com/ffreemt/deepl-scraper-pyppeteer2
License: MIT
Author: freemt
Requires-Python: >=3.8.3,<4.0.0
Classifier: License :: OSI Approved :: MIT License
Classifier: Programming Language :: Python :: 3
Classifier: Programming Language :: Python :: 3.9
Classifier: Programming Language :: Python :: 3.10
Requires-Dist: about-time (>=4.2.1,<5.0.0)
Requires-Dist: fastapi (>=0.89.1,<0.90.0)
Requires-Dist: get-ppbrowser (>=0.1.3,<0.2.0)
Requires-Dist: logzero (>=1.6.3,<2.0.0)
Requires-Dist: nest-asyncio (>=1.5.6,<2.0.0)
Requires-Dist: pyquery (>=1.4.3,<2.0.0)
Requires-Dist: uvicorn (>=0.13.4,<0.14.0)
Project-URL: Repository, https://github.com/ffreemt/deepl-scraper-pyppeteer2
